[[{"word":1,"tr":"By the sun","aya":1,"sura":91,"ar":"وَالشَّمْسِ"},{"word":2,"tr":"and its brightness,","aya":1,"sura":91,"ar":"وَضُحٰهَا"}],[{"word":1,"tr":"And the moon","aya":2,"sura":91,"ar":"وَالْقَمَرِ"},{"word":2,"tr":"when","aya":2,"sura":91,"ar":"إِذَا"},{"word":3,"tr":"it follows it,","aya":2,"sura":91,"ar":"تَلٰهَا"}],[{"word":1,"tr":"And the day","aya":3,"sura":91,"ar":"وَالنَّهَارِ"},{"word":2,"tr":"when","aya":3,"sura":91,"ar":"إِذَا"},{"word":3,"tr":"it displays it,","aya":3,"sura":91,"ar":"جَلّٰهَا"}],[{"word":1,"tr":"And the night","aya":4,"sura":91,"ar":"وَالَّيْلِ"},{"word":2,"tr":"when","aya":4,"sura":91,"ar":"إِذَا"},{"word":3,"tr":"it covers it,","aya":4,"sura":91,"ar":"يَغْشٰهَا"}],[{"word":1,"tr":"And the heaven","aya":5,"sura":91,"ar":"وَالسَّمَآءِ"},{"word":2,"tr":"and He Who","aya":5,"sura":91,"ar":"وَمَا"},{"word":3,"tr":"constructed it,","aya":5,"sura":91,"ar":"بَنٰهَا"}],[{"word":1,"tr":"And the earth","aya":6,"sura":91,"ar":"وَالْأَرْضِ"},{"word":2,"tr":"and He Who","aya":6,"sura":91,"ar":"وَمَا"},{"word":3,"tr":"spread it,","aya":6,"sura":91,"ar":"طَحٰهَا"}],[{"word":1,"tr":"And (the) soul","aya":7,"sura":91,"ar":"وَنَفْسٍ"},{"word":2,"tr":"and He Who","aya":7,"sura":91,"ar":"وَمَا"},{"word":3,"tr":"proportioned it,","aya":7,"sura":91,"ar":"سَوّٰىهَا"}],[{"word":1,"tr":"And He inspired it","aya":8,"sura":91,"ar":"فَأَلْهَمَهَا"},{"word":2,"tr":"(to understand) what is wrong for it","aya":8,"sura":91,"ar":"فُجُورَهَا"},{"word":3,"tr":"and what is right for it,","aya":8,"sura":91,"ar":"وَتَقْوٰىهَا"}],[{"word":1,"tr":"Indeed,","aya":9,"sura":91,"ar":"قَدْ"},{"word":2,"tr":"he succeeds","aya":9,"sura":91,"ar":"أَفْلَحَ"},{"word":3,"tr":"who","aya":9,"sura":91,"ar":"مَن"},{"word":4,"tr":"purifies it,","aya":9,"sura":91,"ar":"زَكّٰهَا"}],[{"word":1,"tr":"And indeed,","aya":10,"sura":91,"ar":"وَقَدْ"},{"word":2,"tr":"he fails","aya":10,"sura":91,"ar":"خَابَ"},{"word":3,"tr":"who","aya":10,"sura":91,"ar":"مَن"},{"word":4,"tr":"corrupts it.","aya":10,"sura":91,"ar":"دَسّٰهَا"}],[{"word":1,"tr":"Denied","aya":11,"sura":91,"ar":"كَذَّبَتْ"},{"word":2,"tr":"Thamud","aya":11,"sura":91,"ar":"ثَمُودُ"},{"word":3,"tr":"by their transgression,","aya":11,"sura":91,"ar":"بِطَغْوٰىهَآ"}],[{"word":1,"tr":"When","aya":12,"sura":91,"ar":"إِذِ"},{"word":2,"tr":"(was) sent forth","aya":12,"sura":91,"ar":"انۢبَعَثَ"},{"word":3,"tr":"(the) most wicked of them.","aya":12,"sura":91,"ar":"أَشْقٰهَا"}],[{"word":1,"tr":"But said","aya":13,"sura":91,"ar":"فَقَالَ"},{"word":2,"tr":"to them","aya":13,"sura":91,"ar":"لَهُمْ"},{"word":3,"tr":"(the) Messenger","aya":13,"sura":91,"ar":"رَسُولُ"},{"word":4,"tr":"(of) Allah,","aya":13,"sura":91,"ar":"اللَّهِ"},{"word":5,"tr":"`(It is the) she-camel","aya":13,"sura":91,"ar":"نَاقَةَ"},{"word":6,"tr":"(of) Allah","aya":13,"sura":91,"ar":"اللَّهِ"},{"word":7,"tr":"and her drink.`","aya":13,"sura":91,"ar":"وَسُقْيٰهَا"}],[{"word":1,"tr":"But they denied him,","aya":14,"sura":91,"ar":"فَكَذَّبُوهُ"},{"word":2,"tr":"and they hamstrung her.","aya":14,"sura":91,"ar":"فَعَقَرُوهَا"},{"word":3,"tr":"So destroyed","aya":14,"sura":91,"ar":"فَدَمْدَمَ"},{"word":4,"tr":"them","aya":14,"sura":91,"ar":"عَلَيْهِمْ"},{"word":5,"tr":"their Lord","aya":14,"sura":91,"ar":"رَبُّهُم"},{"word":6,"tr":"for their sin","aya":14,"sura":91,"ar":"بِذَنۢبِهِمْ"},{"word":7,"tr":"and leveled them.","aya":14,"sura":91,"ar":"فَسَوّٰىهَا"}],[{"word":1,"tr":"And not","aya":15,"sura":91,"ar":"وَلَا"},{"word":2,"tr":"He fears","aya":15,"sura":91,"ar":"يَخَافُ"},{"word":3,"tr":"its consequences.","aya":15,"sura":91,"ar":"عُقْبٰهَا"}]]
