[[{"word":1,"tr":"By the night","aya":1,"sura":92,"ar":"وَالَّيْلِ"},{"word":2,"tr":"when","aya":1,"sura":92,"ar":"إِذَا"},{"word":3,"tr":"it covers,","aya":1,"sura":92,"ar":"يَغْشٰى"}],[{"word":1,"tr":"And the day","aya":2,"sura":92,"ar":"وَالنَّهَارِ"},{"word":2,"tr":"when","aya":2,"sura":92,"ar":"إِذَا"},{"word":3,"tr":"it shines in brightness,","aya":2,"sura":92,"ar":"تَجَلّٰى"}],[{"word":1,"tr":"And He Who created","aya":3,"sura":92,"ar":"وَمَا خَلَقَ"},{"word":2,"tr":"the male","aya":3,"sura":92,"ar":"الذَّكَرَ"},{"word":3,"tr":"and the female,","aya":3,"sura":92,"ar":"وَالْأُنثٰىٓ"}],[{"word":1,"tr":"Indeed,","aya":4,"sura":92,"ar":"إِنَّ"},{"word":2,"tr":"your efforts","aya":4,"sura":92,"ar":"سَعْيَكُمْ"},{"word":3,"tr":"(are) surely diverse.","aya":4,"sura":92,"ar":"لَشَتّٰى"}],[{"word":1,"tr":"Then as for","aya":5,"sura":92,"ar":"فَأَمَّا"},{"word":2,"tr":"(him) who","aya":5,"sura":92,"ar":"مَنْ"},{"word":3,"tr":"gives","aya":5,"sura":92,"ar":"أَعْطٰى"},{"word":4,"tr":"and fears,","aya":5,"sura":92,"ar":"وَاتَّقٰى"}],[{"word":1,"tr":"And believes","aya":6,"sura":92,"ar":"وَصَدَّقَ"},{"word":2,"tr":"in the best,","aya":6,"sura":92,"ar":"بِالْحُسْنٰى"}],[{"word":1,"tr":"Then We will ease him","aya":7,"sura":92,"ar":"فَسَنُيَسِّرُهُۥ"},{"word":2,"tr":"towards [the] ease.","aya":7,"sura":92,"ar":"لِلْيُسْرٰى"}],[{"word":1,"tr":"But as for","aya":8,"sura":92,"ar":"وَأَمَّا"},{"word":2,"tr":"(him) who","aya":8,"sura":92,"ar":"مَنۢ"},{"word":3,"tr":"withholds","aya":8,"sura":92,"ar":"بَخِلَ"},{"word":4,"tr":"and considers himself free from need,","aya":8,"sura":92,"ar":"وَاسْتَغْنٰى"}],[{"word":1,"tr":"And denies","aya":9,"sura":92,"ar":"وَكَذَّبَ"},{"word":2,"tr":"the best,","aya":9,"sura":92,"ar":"بِالْحُسْنٰى"}],[{"word":1,"tr":"Then We will ease him","aya":10,"sura":92,"ar":"فَسَنُيَسِّرُهُۥ"},{"word":2,"tr":"towards [the] difficulty.","aya":10,"sura":92,"ar":"لِلْعُسْرٰى"}],[{"word":1,"tr":"And not","aya":11,"sura":92,"ar":"وَمَا"},{"word":2,"tr":"will avail","aya":11,"sura":92,"ar":"يُغْنِى"},{"word":3,"tr":"him","aya":11,"sura":92,"ar":"عَنْهُ"},{"word":4,"tr":"his wealth","aya":11,"sura":92,"ar":"مَالُهُۥٓ"},{"word":5,"tr":"when","aya":11,"sura":92,"ar":"إِذَا"},{"word":6,"tr":"he falls.","aya":11,"sura":92,"ar":"تَرَدّٰىٓ"}],[{"word":1,"tr":"Indeed,","aya":12,"sura":92,"ar":"إِنَّ"},{"word":2,"tr":"upon Us","aya":12,"sura":92,"ar":"عَلَيْنَا"},{"word":3,"tr":"(is) the guidance.","aya":12,"sura":92,"ar":"لَلْهُدٰى"}],[{"word":1,"tr":"And indeed,","aya":13,"sura":92,"ar":"وَإِنَّ"},{"word":2,"tr":"for Us","aya":13,"sura":92,"ar":"لَنَا"},{"word":3,"tr":"(is) the Hereafter","aya":13,"sura":92,"ar":"لَلْأَخِرَةَ"},{"word":4,"tr":"and the first (life).","aya":13,"sura":92,"ar":"وَالْأُولٰى"}],[{"word":1,"tr":"So I warn you","aya":14,"sura":92,"ar":"فَأَنذَرْتُكُمْ"},{"word":2,"tr":"(of) a Fire","aya":14,"sura":92,"ar":"نَارًا"},{"word":3,"tr":"blazing,","aya":14,"sura":92,"ar":"تَلَظّٰى"}],[{"word":1,"tr":"Not","aya":15,"sura":92,"ar":"لَا"},{"word":2,"tr":"will burn (in) it","aya":15,"sura":92,"ar":"يَصْلٰهَآ"},{"word":3,"tr":"except","aya":15,"sura":92,"ar":"إِلَّا"},{"word":4,"tr":"the most wretched,","aya":15,"sura":92,"ar":"الْأَشْقَى"}],[{"word":1,"tr":"The one who","aya":16,"sura":92,"ar":"الَّذِى"},{"word":2,"tr":"denied","aya":16,"sura":92,"ar":"كَذَّبَ"},{"word":3,"tr":"and turned away.","aya":16,"sura":92,"ar":"وَتَوَلّٰى"}],[{"word":1,"tr":"But will be removed from it","aya":17,"sura":92,"ar":"وَسَيُجَنَّبُهَا"},{"word":2,"tr":"the righteous,","aya":17,"sura":92,"ar":"الْأَتْقَى"}],[{"word":1,"tr":"The one who","aya":18,"sura":92,"ar":"الَّذِى"},{"word":2,"tr":"gives","aya":18,"sura":92,"ar":"يُؤْتِى"},{"word":3,"tr":"his wealth","aya":18,"sura":92,"ar":"مَالَهُۥ"},{"word":4,"tr":"purifying himself,","aya":18,"sura":92,"ar":"يَتَزَكّٰى"}],[{"word":1,"tr":"And not","aya":19,"sura":92,"ar":"وَمَا"},{"word":2,"tr":"for anyone","aya":19,"sura":92,"ar":"لِأَحَدٍ"},{"word":3,"tr":"with him","aya":19,"sura":92,"ar":"عِندَهُۥ"},{"word":4,"tr":"any","aya":19,"sura":92,"ar":"مِن"},{"word":5,"tr":"favor","aya":19,"sura":92,"ar":"نِّعْمَةٍ"},{"word":6,"tr":"to be recompensed","aya":19,"sura":92,"ar":"تُجْزٰىٓ"}],[{"word":1,"tr":"Except","aya":20,"sura":92,"ar":"إِلَّا"},{"word":2,"tr":"seeking","aya":20,"sura":92,"ar":"ابْتِغَآءَ"},{"word":3,"tr":"(the) Countenance","aya":20,"sura":92,"ar":"وَجْهِ"},{"word":4,"tr":"(of) his Lord,","aya":20,"sura":92,"ar":"رَبِّهِ"},{"word":5,"tr":"the Most High.","aya":20,"sura":92,"ar":"الْأَعْلٰى"}],[{"word":1,"tr":"And soon, surely","aya":21,"sura":92,"ar":"وَلَسَوْفَ"},{"word":2,"tr":"he will be pleased.","aya":21,"sura":92,"ar":"يَرْضٰى"}]]
